setup.py
bin/reviewday
reviewday/__init__.py
reviewday/gerrit.py
reviewday/html_helper.py
reviewday/launchpad.py
reviewday/mergeprop.py
reviewday/smokestack.py
reviewday/util.py
reviewday.egg-info/PKG-INFO
reviewday.egg-info/SOURCES.txt
reviewday.egg-info/dependency_links.txt
reviewday.egg-info/requires.txt
reviewday.egg-info/top_level.txt