Metadata-Version: 1.0
Name: reviewday
Version: 0.1.0
Summary: Report generator for OpenStack code reviews.
Home-page: https://github/dprince/reviewday
Author: Dan Prince
Author-email: dan.prince@rackspace.com
License: BSD
Keywords: OpenStack HTML report generator
Platform: UNKNOWN
Classifier: Development Status :: 4 - Beta
Classifier: Topic :: Utilities
Classifier: License :: OSI Approved :: BSD License
